loady/VERSION
loady/__init__.py
loady/code.py
loady/config.py
loady/data.py
loady/files.py
loady/importer.py
loady/library.py
loady/raw.py
loady/sys_path.py
loady/whitelist.py
test/loady/__init__.py
test/loady/code_test.py
test/loady/importer_test.py
test/loady/raw_test.py
test/loady/whitelist_test.py
test/sub/__init__.py
test/sub/foo.py
test/sub/bar/__init__.py
test/sub/bar/bar.py
test/sub/modules/__init__.py
test/sub/modules/ambiguous.py
test/sub/modules/same.py
test/sub/modules/single.py
test/sub/modules/under_score.py
test/sub/modules/underscore.py
loady-1.8.12.dist-info/LICENSE
loady-1.8.12.dist-info/LICENSE.txt
loady-1.8.12.dist-info/METADATA
loady-1.8.12.dist-info/WHEEL
loady-1.8.12.dist-info/top_level.txt
loady-1.8.12.dist-info/RECORD
