Metadata-Version: 2.1
Name: loady
Version: 1.8.12
Summary: loady lets you load Python libraries, JSON and raw text dynamically from git
Home-page: http://github.com/timedata-org/loady
Download-URL: http://github.com/timedata-org/loady/archive/1.8.12.tar.gz
Author: Tom Ritchford
Author-email: tom@swirly.com
License: MIT
Keywords: git,import
Platform: UNKNOWN
Classifier: Development Status :: 4 - Beta
Classifier: License :: OSI Approved :: MIT License
Classifier: Programming Language :: Python :: 3.4
Classifier: Programming Language :: Python :: 3.5
Classifier: Programming Language :: Python :: 3.6
License-File: LICENSE
License-File: LICENSE.txt
Requires-Dist: wheel
Requires-Dist: GitPython
Requires-Dist: beautifulsoup4
Requires-Dist: requests
Requires-Dist: pyyaml
